[
  {
    "title": "인천아파트경매 논현동 한화 에코메트로11단지 아파트 2차 경매",
    "content": "인천아파트경매 논현동 한화 에코메트로11단지 43평 2차 경매 감정가 6억5900만원 2차 입찰가 4억6130만원~ 인천 남동구 논현동 774-1, 에코메트로11단지 1104동 1201호 (논고개로 17, 한화11단지) 사건번호 2024타경554195 매각기일 2025년07월18일(금) 감정가 6억5900만원 2차 입찰시작가 4억6130만원~ 인천지방법원 본원 경매 12계 인천 논현동...",
    "date": "",
    "url": "https://blog.naver.com/10hotels/223909970203",
    "source": "네이버 블로그",
    "type": "blog",
    "keyword": "에코메트로",
    "search_rank": 1
  },
  {
    "title": "인천아파트경매 에코메트로 7단지 급매",
    "content": "그곳은 바로 ‘에코메트로 7단지'인데요! 이 단지는 논현동 핵심 주거지에 위치해, 생활 인프라와 교통 접근성이 우수한 입지에 자리하고 있어요. 게다가, 급매 형태의 경매 물건이라 일반 매매보다 훨씬 매력적인 낙찰가를 기대할 수 있어요. 과연 급매가격대인지 미래가치를 판단할 수 있는 호재, 시세 등을 비교하며 경매 물건을 판단해 봐요! 7단지 소개...",
    "date": "",
    "url": "https://blog.naver.com/dsd_auction/223910128868",
    "source": "네이버 블로그",
    "type": "blog",
    "keyword": "에코메트로",
    "search_rank": 2
  },
  {
    "title": "논현에코메트로 12단지 리모델링 변화",
    "content": "오늘은 만족스럽게 시공을 마무리한 논현에코메트로12단지 리모델링 후기를 자세하게 전해드리도록 할게요. 이번 공사는 33평 전체 리모델링을 의뢰해주셨고 꼼꼼하게 상담과 소통 후 고객님의 니즈에 맞는 인테리어, 현재 트렌드에 맞는 시공으로 계획 시공한 공간이랍니다. 논현12단지 출처:네이버 논현12단지 경우에는 메인 침실과 드레스룸...",
    "date": "",
    "url": "https://blog.naver.com/interior_park213/223910008102",
    "source": "네이버 블로그",
    "type": "blog",
    "keyword": "에코메트로",
    "search_rank": 3
  },
  {
    "title": "논현동 에코메트로12단지 한화꿈에그린 33평형 C타입(112C㎡) 인테리어 시공 후기",
    "content": "ENTRANCE LIVING ROOM KITCHEN BATHROOM ROOM #남동구인테리어 #논현동인테리어 #남동구논현동인테리어 #논현동에코메트로인테리어 #에코메트로인테리어 #에코메트로33평인테리어 #한화꿈에그린인테리어 #논현에코인테리어 #12단지인테리어 #한화꿈에그린12단지인테리어 #30평대인테리어 #인천시남동구인테리어 #3D시안 #옥련동큐브인테리어...",
    "date": "",
    "url": "https://blog.naver.com/misplay75/223912100258",
    "source": "네이버 블로그",
    "type": "blog",
    "keyword": "에코메트로",
    "search_rank": 4
  },
  {
    "title": "인천아파트 경매물건. 논현동 에코메트로11단지한화꿈에그린 경매 43평 ★ 초품아·소래포구역 2024타경554195",
    "content": "▷ 인천광역시 남동구 논고개로 17 에코메트로11단지한화꿈에그린 1104동 12층 1201호 입찰 보증금은 최저매각금액의 10%인 46,130,000원 준비 하시면 됩니다. ※ 말소... 호가 6억3천 ~ 7억5천 2차경매 최저가 461,300,000원 마지막 실거래가 625,000,000원 수인분당선 소래포구역 고잔초를 품은 초품아 오션뷰 조망 가능 11단지한화꿈에그린...",
    "date": "",
    "url": "https://blog.naver.com/gosja/223909424222",
    "source": "네이버 블로그",
    "type": "blog",
    "keyword": "에코메트로",
    "search_rank": 5
  },
  {
    "title": "인천 남동구 논현동 에코메트로9단지 한화꿈에그린아파트 인테리어 by 채움디자인",
    "url": "https://www.youtube.com/shorts/MQU-s7gtOF4",
    "channel": "페어피스리뷰",
    "views": "",
    "upload_time": "",
    "thumbnail": "https://i.ytimg.com/vi/MQU-s7gtOF4/hq720_2.jpg?sqp=-oaymwExCNAFEJQDSFryq4qpAyMIARUAAIhCGADwAQH4Ac4FgAKACooCDAgAEAEYYCBlKFkwDw==&rs=AOn4CLAmFknRQtVqGxd5-CEQokXr9Pc0YQ",
    "type": "youtube",
    "keyword": "에코메트로",
    "search_rank": 1,
    "date": ""
  },
  {
    "title": "인천 남동구 논현동 한화꿈에그린에코메트로6단지아파트 인테리어 by 스타인테리어",
    "url": "https://www.youtube.com/watch?v=RGH51PbSBIc&pp=ygUP7JeQ7L2U66mU7Yq466Gc",
    "channel": "페어피스리뷰",
    "views": "",
    "upload_time": "",
    "thumbnail": "https://i.ytimg.com/vi/RGH51PbSBIc/hq720.jpg?sqp=-oaymwExCNAFEJQDSFryq4qpAyMIARUAAIhCGAHwAQH4Af4JgALQBYoCDAgAEAEYZSBlKGUwDw==&rs=AOn4CLDJYxUyQyHGQ7SGAh-9RSj1ZKn9hg",
    "type": "youtube",
    "keyword": "에코메트로",
    "search_rank": 2,
    "date": ""
  },
  {
    "title": "[갭투자 시리즈] 인천 남동구 2억 대 갭투자 TOP5",
    "url": "https://www.youtube.com/shorts/UFBqBgtx4j8",
    "channel": "마테크",
    "views": "",
    "upload_time": "",
    "thumbnail": "https://i.ytimg.com/vi/UFBqBgtx4j8/hq720_2.jpg?sqp=-oaymwExCNAFEJQDSFryq4qpAyMIARUAAIhCGADwAQH4AbYIgAKAD4oCDAgAEAEYZyBnKGcwDw==&rs=AOn4CLAjcydXchoK4MtGJ6F2rl5amklK9Q",
    "type": "youtube",
    "keyword": "에코메트로",
    "search_rank": 3,
    "date": ""
  },
  {
    "title": "💡“젊은 도시 + 일자리 폭발 + 학세권 = 아테라 ”에코델타시티 중심의기대작 84타입 4억대 분양🌱“부동산 눈 있는 사람들, 다 여기로 간다 – 금호 아테라 리뷰!”",
    "url": "https://www.youtube.com/shorts/9_CJo1ovoBo",
    "channel": "황금구두",
    "views": "",
    "upload_time": "",
    "thumbnail": "https://i.ytimg.com/vi/9_CJo1ovoBo/hq720_2.jpg?sqp=-oaymwExCNAFEJQDSFryq4qpAyMIARUAAIhCGADwAQH4AbYIgAKAD4oCDAgAEAEYciBTKDwwDw==&rs=AOn4CLBKjGBMQ-k3yb_AOhtkQPB5Xt0q2A",
    "type": "youtube",
    "keyword": "에코메트로",
    "search_rank": 4,
    "date": ""
  },
  {
    "title": "검단-김포 5호선 신속예타 발표 한달 전🧐검단신도시 진짜 주목해야하는 곳💯아라역VS신검단중앙역 어디가 정답일까요⁉️GTX-D/인천1호선/5호선/9호선",
    "url": "https://www.youtube.com/watch?v=UQUyoVQfCG8&pp=ygUP7JeQ7L2U66mU7Yq466Gc",
    "channel": "부동산프로 남수란",
    "views": "",
    "upload_time": "",
    "thumbnail": "https://i.ytimg.com/vi/UQUyoVQfCG8/hq720.jpg?sqp=-oaymwEXCNAFEJQDSFryq4qpAwkIARUAAIhCGAE=&rs=AOn4CLDI0PldQBtlCsw4W5Gz39SuhXzsEQ",
    "type": "youtube",
    "keyword": "에코메트로",
    "search_rank": 5,
    "date": ""
  },
  {
    "title": "💡“젊은 도시 + 일자리 폭발 + 학세권 = 아테라 ”에코델타시티 중심의기대작 84타입 4억대 분양🌱“부동산 눈 있는 사람들, 다 여기로 간다 – 금호 아테라 리뷰!”",
    "url": "https://www.youtube.com/shorts/tSVW5bhGHBo",
    "channel": "황금구두",
    "views": "",
    "upload_time": "",
    "thumbnail": "https://i.ytimg.com/vi/tSVW5bhGHBo/hq720_2.jpg?sqp=-oaymwExCNAFEJQDSFryq4qpAyMIARUAAIhCGADwAQH4AbYIgAKAD4oCDAgAEAEYZSBWKEowDw==&rs=AOn4CLBY3hr6sLKR1Aht1Zyo0iTm9p03cw",
    "type": "youtube",
    "keyword": "에코메트로",
    "search_rank": 6,
    "date": ""
  },
  {
    "title": "역대급으로 모델링 바뀐 게임? 7월 출시 예정작 같이봐",
    "url": "https://www.youtube.com/watch?v=1P50FTXu7MI&t=247s&pp=ygUP7JeQ7L2U66mU7Yq466Gc",
    "channel": "G띠",
    "views": "",
    "upload_time": "",
    "thumbnail": "https://i.ytimg.com/vi/1P50FTXu7MI/hq720.jpg?sqp=-oaymwEXCNAFEJQDSFryq4qpAwkIARUAAIhCGAE=&rs=AOn4CLA3UMq_h2z8vwzIf42pT-WH6ZATsw",
    "type": "youtube",
    "keyword": "에코메트로",
    "search_rank": 7,
    "date": ""
  },
  {
    "title": "프루티거 에어로 스타일 스토어#shorts",
    "url": "https://www.youtube.com/shorts/-xI8fQu7s08",
    "channel": "에어드림 테이프",
    "views": "",
    "upload_time": "",
    "thumbnail": "https://i.ytimg.com/vi/-xI8fQu7s08/hq720.jpg?sqp=-oaymwExCNAFEJQDSFryq4qpAyMIARUAAIhCGADwAQH4AbYIgAKAD4oCDAgAEAEYUyBfKGUwDw==&rs=AOn4CLCUd0TKUvyilkIPveug0MutCM4Xzg",
    "type": "youtube",
    "keyword": "에코메트로",
    "search_rank": 8,
    "date": ""
  }
]